show_weather_data/__init__.py
show_weather_data-0.0.1.dist-info/LICENSE.txt
show_weather_data-0.0.1.dist-info/METADATA
show_weather_data-0.0.1.dist-info/WHEEL
show_weather_data-0.0.1.dist-info/top_level.txt
show_weather_data-0.0.1.dist-info/RECORD
